affinitree-0.23.0.dist-info/METADATA
affinitree-0.23.0.dist-info/WHEEL
affinitree-0.23.0.dist-info/licenses/binary-license.html
affinitree-0.23.0.dist-info/licenses/LICENSE-APACHE
affinitree/affinitree.pyi
affinitree/builder/py.typed
affinitree/builder/__init__.py
affinitree/builder/__init__.pyi
affinitree/plot.py
affinitree/py.typed
affinitree/pytorch.py
affinitree/schema/py.typed
affinitree/schema/__init__.py
affinitree/schema/__init__.pyi
affinitree/tests/res/iris_4-5-5-3.npz
affinitree/tests/res/iris_4-5-5-3.pt
affinitree/tests/test_affines.py
affinitree/tests/test_afftree.py
affinitree/tests/test_distillation.py
affinitree/tests/test_plot.py
affinitree/tests/test_polytope.py
affinitree/tests/test_schema.py
affinitree/tests/__init__.py
affinitree/__init__.py
affinitree/affinitree.pypy310-pp73-win_amd64.pyd
affinitree-0.23.0.dist-info/RECORD
