Metadata-Version: 2.4
Name: affinitree
Version: 0.23.0
Classifier: Intended Audience :: Science/Research
Classifier: License :: OSI Approved :: Apache Software License
Classifier: Programming Language :: Python :: 3
Classifier: Programming Language :: Python :: 3.8
Classifier: Programming Language :: Python :: 3.9
Classifier: Programming Language :: Python :: 3.10
Classifier: Programming Language :: Python :: 3.11
Classifier: Programming Language :: Python :: 3.12
Classifier: Programming Language :: Python
Classifier: Programming Language :: Python :: Implementation :: CPython
Classifier: Programming Language :: Python :: Implementation :: PyPy
Classifier: Programming Language :: Rust
Classifier: Operating System :: OS Independent
Classifier: Topic :: Scientific/Engineering :: Artificial Intelligence
Classifier: Typing :: Typed
Requires-Dist: numpy>=1.16.0
Requires-Dist: scipy>=0.19.0
Requires-Dist: matplotlib>=3.8.0
Requires-Dist: seaborn>=0.4.0
Requires-Dist: pytest>=6.2.5 ; extra == 'test'
Provides-Extra: test
License-File: binary-license.html
License-File: LICENSE-APACHE
Summary: Distillation of piecewise linear neural networks into decision trees
Keywords: affinitree,afftree,distillation,XAI
License: Apache-2.0
Requires-Python: >=3.8
Project-URL: repository, https://github.com/Conturing/affinitree-py
